{
  "no": "紫079",
  "appear": "第3弾-2",
  "appearPatterns": [
    "探索(武将): 24/04/17〜",
    "武将獲得: 24/04/17〜"
  ],
  "id": "089cf04678f8d99cf336a07750f8e537",
  "detailImageId": "aa5706e7a2bd423e336fedcc0b3f2e70",
  "name": "盧綰",
  "kanaName": "ろわん",
  "color": {
    "name": "紫",
    "r": "140",
    "g": "0",
    "b": "120"
  },
  "period": "春秋戦国",
  "cost": "2.0",
  "unitType": "剣豪",
  "strat": {
    "name": "朋友の魂",
    "kanaName": "ほうゆうのたましい",
    "cost": "4",
    "description": "【ため計略】（使用すると移動と兵種アクションができなくなり、一定時間後に計略が発動する。この計略は反計されない）<br>武力と移動速度が上がり、兵力が回復する。ただし自城に戻れなくなり、効果終了時に必要士気があると再度ためを開始する。この効果は連続して発動するたびに大きくなる",
    "categories": [
      "強化",
      "回復",
      "ため計略"
    ],
    "time": "知力時間",
    "range": "db0f1158a4038d7c1a1f908c8750498d"
  },
  "power": "8",
  "intelligentzia": "2",
  "skill": [
    {
      "name": "防柵",
      "shortName": "柵",
      "description": "敵部隊の動きを阻害する障害物「柵」を部隊前方に配置した状態で開戦します"
    }
  ],
  "kabuki": "0",
  "url": {
    "official": "https://eiketsu-taisen.net/datalist/?s=general&c=089cf04678f8d99cf336a07750f8e537",
    "atWiki": "https://w.atwiki.jp/eiketsu-taisen/pages/1602.html",
    "gameWiki": "https://eiketsudb.gamewiki.jp/%e6%ad%a6%e5%b0%86%e3%82%ab%e3%83%bc%e3%83%89_2110"
  }
}