{
  "no": "緋067",
  "appear": "第2弾-1",
  "appearPatterns": [
    "探索(武将): 22/12/21〜",
    "武将獲得: 22/12/21〜"
  ],
  "id": "6add83d36b78ab7c34c908540abc58ae",
  "detailImageId": "ea8c3d71ef7a2443f06fe30172cf25e7",
  "name": "平盛国",
  "kanaName": "たいらのもりくに",
  "color": {
    "name": "緋",
    "r": "180",
    "g": "25",
    "b": "27"
  },
  "period": "平安",
  "cost": "2.5",
  "unitType": "騎兵",
  "strat": {
    "name": "神速の誉れ",
    "kanaName": "しんそくのほまれ",
    "cost": "6",
    "description": "武力と移動速度が上がり、効果終了時に自軍の士気が上がる",
    "categories": [
      "強化"
    ],
    "time": "知力時間",
    "range": "db0f1158a4038d7c1a1f908c8750498d"
  },
  "power": "8",
  "intelligentzia": "4",
  "skill": [
    {
      "name": "技巧",
      "shortName": "技",
      "description": "コストに応じて流派ゲージが増加した状態で開戦します"
    },
    {
      "name": "先陣",
      "shortName": "先",
      "description": "開戦から一定時間、武力と知力が上がります"
    }
  ],
  "kabuki": "30",
  "url": {
    "official": "https://eiketsu-taisen.net/datalist/?s=general&c=6add83d36b78ab7c34c908540abc58ae",
    "gameWiki": "https://eiketsudb.gamewiki.jp/%e6%ad%a6%e5%b0%86%e3%82%ab%e3%83%bc%e3%83%89_457"
  }
}