{
  "no": "琥048",
  "appear": "第3弾-2",
  "id": "75c8d00a001e3f39115eaaa445e4f5cb",
  "detailImageId": "1dc8fe4fb36bb2a2d4004862db399bfc",
  "name": "晋文公",
  "kanaName": "しんのぶんこう",
  "color": {
    "name": "琥",
    "r": "230",
    "g": "135",
    "b": "0"
  },
  "period": "春秋戦国",
  "cost": "2.5",
  "unitType": "弓兵",
  "strat": {
    "name": "晋水の霸者",
    "kanaName": "しんすいのはしゃ",
    "cost": "6",
    "description": "武力が上がり、走射時間が延びる。さらに一定距離走射状態を維持すると、接触した敵にダメージを与えて弾くようになる。この効果で敵を弾くたびに武力が上がるが、敵を弾くと走射は終了する",
    "categories": [
      "強化"
    ],
    "time": "知力時間",
    "range": "db0f1158a4038d7c1a1f908c8750498d"
  },
  "power": "8",
  "intelligentzia": "6",
  "skill": [
    {
      "name": "防柵",
      "shortName": "柵",
      "description": "敵部隊の動きを阻害する障害物「柵」を部隊前方に配置した状態で開戦します"
    },
    {
      "name": "先陣",
      "shortName": "先",
      "description": "開戦から一定時間、武力と知力が上がります"
    }
  ],
  "kabuki": "9",
  "url": {
    "official": "https://eiketsu-taisen.net/datalist/?s=general&c=75c8d00a001e3f39115eaaa445e4f5cb",
    "atWiki": "https://w.atwiki.jp/eiketsu-taisen/pages/1536.html",
    "gameWiki": "https://eiketsudb.gamewiki.jp/%e6%ad%a6%e5%b0%86%e3%82%ab%e3%83%bc%e3%83%89_2107"
  }
}