{
  "no": "PL018",
  "appear": "第1弾-PL",
  "id": "45f2e5d5d940eb3b9b480dbee7d3e13b",
  "detailImageId": "baa7f274cc93a47e30e723d4cfd89e22",
  "name": "杉元佐一",
  "kanaName": "すぎもとさいち",
  "color": {
    "name": "緋",
    "r": "180",
    "g": "25",
    "b": "27"
  },
  "period": "特殊",
  "cost": "2.5",
  "unitType": "鉄砲隊",
  "strat": {
    "name": "鬼神の一等卒",
    "kanaName": "ワンマンアーミー",
    "cost": "5",
    "description": "武力が上がり、兵力が徐々に回復する。<br>ただし射撃ができなくなる",
    "categories": [
      "強化",
      "回復"
    ],
    "time": "知力時間",
    "range": "db0f1158a4038d7c1a1f908c8750498d"
  },
  "power": "8",
  "intelligentzia": "6",
  "skill": [
    {
      "name": "復活",
      "shortName": "活",
      "description": "撤退した際、復活するために必要な時間が減少します"
    },
    {
      "name": "気合",
      "shortName": "気",
      "description": "通常の戦闘で受けたダメージの一部を一定時間ごとに回復します"
    }
  ],
  "kabuki": "10",
  "url": {
    "official": "https://eiketsu-taisen.net/datalist/?s=general&c=45f2e5d5d940eb3b9b480dbee7d3e13b",
    "atWiki": "https://w.atwiki.jp/eiketsu-taisen/pages/562.html",
    "gameWiki": "https://eiketsudb.gamewiki.jp/%e6%ad%a6%e5%b0%86%e3%82%ab%e3%83%bc%e3%83%89_428"
  }
}